pulumi_chronosphere/__init__.py
pulumi_chronosphere/_inputs.py
pulumi_chronosphere/_utilities.py
pulumi_chronosphere/azure_metrics_integration.py
pulumi_chronosphere/blackhole_alert_notifier.py
pulumi_chronosphere/bucket.py
pulumi_chronosphere/bucket_data_source.py
pulumi_chronosphere/classic_dashboard.py
pulumi_chronosphere/collection.py
pulumi_chronosphere/collection_data_source.py
pulumi_chronosphere/consumption_budget.py
pulumi_chronosphere/consumption_config.py
pulumi_chronosphere/dashboard.py
pulumi_chronosphere/dataset.py
pulumi_chronosphere/derived_label.py
pulumi_chronosphere/derived_metric.py
pulumi_chronosphere/drop_rule.py
pulumi_chronosphere/email_alert_notifier.py
pulumi_chronosphere/gcp_metrics_integration.py
pulumi_chronosphere/log_allocation_config.py
pulumi_chronosphere/log_control_config.py
pulumi_chronosphere/log_ingest_config.py
pulumi_chronosphere/logscale_action.py
pulumi_chronosphere/logscale_alert.py
pulumi_chronosphere/mapping_rule.py
pulumi_chronosphere/monitor.py
pulumi_chronosphere/notification_policy.py
pulumi_chronosphere/opsgenie_alert_notifier.py
pulumi_chronosphere/otel_metrics_ingestion.py
pulumi_chronosphere/outputs.py
pulumi_chronosphere/pagerduty_alert_notifier.py
pulumi_chronosphere/provider.py
pulumi_chronosphere/pulumi-plugin.json
pulumi_chronosphere/py.typed
pulumi_chronosphere/recording_rule.py
pulumi_chronosphere/resource_pools_config.py
pulumi_chronosphere/rollup_rule.py
pulumi_chronosphere/service_account.py
pulumi_chronosphere/service_data_source.py
pulumi_chronosphere/slack_alert_notifier.py
pulumi_chronosphere/slo.py
pulumi_chronosphere/team.py
pulumi_chronosphere/trace_jaeger_remote_sampling_strategy.py
pulumi_chronosphere/trace_metrics_rule.py
pulumi_chronosphere/trace_tail_sampling_rules.py
pulumi_chronosphere/victorops_alert_notifier.py
pulumi_chronosphere/webhook_alert_notifier.py
pulumi_chronosphere/config/__init__.py
pulumi_chronosphere/config/__init__.pyi
pulumi_chronosphere/config/vars.py
pulumi_chronosphere-0.9.10.dist-info/METADATA
pulumi_chronosphere-0.9.10.dist-info/WHEEL
pulumi_chronosphere-0.9.10.dist-info/top_level.txt
pulumi_chronosphere-0.9.10.dist-info/RECORD
