Metadata-Version: 2.4
Name: pulumi_chronosphere
Version: 0.9.10
Summary: A Pulumi package for creating and managing Chronosphere resources.
Home-page: https://chronosphere.io
License: Apache-2.0
Project-URL: Homepage, https://chronosphere.io
Project-URL: Repository, https://github.com/chronosphereio/pulumi-chronosphere
Keywords: pulumi,chronosphere
Requires-Python: >=3.7
Requires-Dist: parver>=0.2.1
Requires-Dist: pulumi<4.0.0,>=3.0.0
Requires-Dist: semver>=2.8.1
Dynamic: home-page
Dynamic: requires-python
